Workbook

Sheet Orçamento
B3: [ PLANILHA ORÇAMENTO FAMILIAR ] - LANÇAMENTOS DE VALORES
C5: JANEIRO | D5: FEVEREIRO | E5: MARÇO | F5: ABRIL | G5: MAIO | H5: JUNHO | I5: JULHO | J5: AGOSTO | K5: SETEMBRO | L5: OUTUBRO | M5: NOVEMBRO | N5: DEZEMBRO | O5: TOTAL | P5: TENDÊNCIA
B6: RECEITAS | C6: =C12 -> 735 | D6: =D12 -> 830 | E6: =E12 -> 700 | F6: =F12 -> 750 | G6: =G12 -> 630 | H6: =H12 -> 0 | I6: =I12 -> 0 | J6: =J12 -> 0 | ... N6: =N12 -> 0 | O6: =SUM(C6:N6) -> 3645
B7: DESPESAS | C7: =C22+C34+C43+C50+C60+C72+C82+C88 -> 452 | D7: =D22+D34+D43+D50+D60+D72+D82+D88 -> 392 | E7: =E22+E34+E43+E50+E60+E72+E82+E88 -> 745 | F7: =F22+F34+F43+F50+F60+F72+F82+F88 -> 330 | G7: =G22+G34+G43+G50+G60+G72+G82+G88 -> 200 | H7: =H22+H34+H43+H50+H60+H72+H82+H88 -> 0 | I7: =I22+I34+I43+I50+I60+I72+I82+I88 -> 0 | J7: =J22+J34+J43+J50+J60+J72+J82+J88 -> 0 | ... N7: =N22+N34+N43+N50+N60+N72+N82+N88 -> 0 | O7: =SUM(C7:N7) -> 2119
B8: SALDO MENSAL | C8: =C6-C7 -> 283 | D8: =D6-D7 -> 438 | E8: =E6-E7 -> -45 | F8: =F6-F7 -> 420 | G8: =G6-G7 -> 430 | H8: =H6-H7 -> 0 | I8: =I6-I7 -> 0 | J8: =J6-J7 -> 0 | ... O8: =O6-O7 -> 1526
B9: SALDO ACUMULADO | C9: =C8 -> 283 | D9: =C9+D8 -> 721 | E9: =D9+E8 -> 676 | F9: =E9+F8 -> 1096 | G9: =F9+G8 -> 1526 | H9: =G9+H8 -> 1526 | I9: =H9+I8 -> 1526 | J9: =I9+J8 -> 1526 | K9: =J9+K8 -> 1526 | ... N9: =M9+N8 -> 1526 | O9: =N9 -> 1526
B11: Descrição de Receitas
B12: COMPOSIÇÃO RECEITA | C12: =SUM(C13:C18) -> 735 | D12: =SUM(D13:D18) -> 830 | E12: =SUM(E13:E18) -> 700 | F12: =SUM(F13:F18) -> 750 | G12: =SUM(G13:G18) -> 630 | H12: =SUM(H13:H18) -> 0 | I12: =SUM(I13:I18) -> 0 | J12: =SUM(J13:J18) -> 0 | ... O12: =SUM(O13:O18) -> 3645
B13: Salários | C13: 180 | D13: 200 | E13: 250 | F13: 250 | G13: 250 | O13: =SUM(C13:N13) -> 1130 | P13: =IFERROR(O13/$O$12,0) -> 0.31001372
B14: 13º. Salário | C14: 0 | D14: 180 | O14: =SUM(C14:N14) -> 180 | P14: =IFERROR(O14/$O$12,0) -> 0.049382716
B15: Férias | C15: 80 | D15: 0 | F15: 250 | O15: =SUM(C15:N15) -> 330 | P15: =IFERROR(O15/$O$12,0) -> 0.090534979
B16: Retirada de Poupança | C16: 120 | D16: 80 | E16: 150 | F16: 100 | G16: 180 | O16: =SUM(C16:N16) -> 630 | P16: =IFERROR(O16/$O$12,0) -> 0.17283951
B17: Retirada de Aplicações | C17: 150 | D17: 120 | E17: 100 | O17: =SUM(C17:N17) -> 370 | P17: =IFERROR(O17/$O$12,0) -> 0.10150892
B18: Outros | C18: 205 | D18: 250 | E18: 200 | F18: 150 | G18: 200 | O18: =SUM(C18:N18) -> 1005 | P18: =IFERROR(O18/$O$12,0) -> 0.27572016
B20: Descrição de Despesas por Categoria
B21: % EM RELAÇÃO À RECEITA | C21: =IFERROR(C22/C$6,0) -> 0.27210884 | D21: =IFERROR(D22/D$6,0) -> 0.28915663 | E21: =IFERROR(E22/E$6,0) -> 0.91428571 | F21: =IFERROR(F22/F$6,0) -> 0.28666667 | G21: =IFERROR(G22/G$6,0) -> 0.20634921 | H21: =IFERROR(H22/H$6,0) -> 0 | I21: =IFERROR(I22/I$6,0) -> 0 | J21: =IFERROR(J22/J$6,0) -> 0 | ... O21: =IFERROR(O22/O$6,0) -> 0.3909465
B22: HABITAÇÃO | C22: =SUM(C23:C31) -> 200 | D22: =SUM(D23:D31) -> 240 | E22: =SUM(E23:E31) -> 640 | F22: =SUM(F23:F31) -> 215 | G22: =SUM(G23:G31) -> 130 | H22: =SUM(H23:H31) -> 0 | I22: =SUM(I23:I31) -> 0 | J22: =SUM(J23:J31) -> 0 | ... O22: =SUM(O23:O31) -> 1425
B23: Aluguel/Prestação | C23: 100 | D23: 100 | E23: 150 | F23: 100 | G23: 50 | O23: =SUM(C23:N23) -> 500 | P23: =IFERROR(O23/$O$22,0) -> 0.35087719
B24: Condomínio | D24: 50 | E24: 50 | O24: =SUM(C24:N24) -> 100 | P24: =IFERROR(O24/$O$22,0) -> 0.070175439
B25: IPTU | C25: 50 | E25: 50 | F25: 45 | O25: =SUM(C25:N25) -> 145 | P25: =IFERROR(O25/$O$22,0) -> 0.10175439
B26: Luz | E26: 300 | O26: =SUM(C26:N26) -> 300 | P26: =IFERROR(O26/$O$22,0) -> 0.21052632
B27: Telefones | O27: =SUM(C27:N27) -> 0 | P27: =IFERROR(O27/$O$22,0) -> 0
B28: TV por Assinatura | C28: 50 | D28: 50 | E28: 50 | F28: 50 | G28: 50 | O28: =SUM(C28:N28) -> 250 | P28: =IFERROR(O28/$O$22,0) -> 0.1754386
B29: Internet | O29: =SUM(C29:N29) -> 0 | P29: =IFERROR(O29/$O$22,0) -> 0
B30: Empregada | D30: 40 | E30: 40 | F30: 20 | G30: 30 | O30: =SUM(C30:N30) -> 130 | P30: =IFERROR(O30/$O$22,0) -> 0.09122807
B31: Outros | O31: =SUM(C31:N31) -> 0 | P31: =IFERROR(O31/$O$22,0) -> 0
B33: % EM RELAÇÃO À RECEITA | C33: =IFERROR(C34/C$6,0) -> 0.016326531 | D33: =IFERROR(D34/D$6,0) -> 0.012048193 | E33: =IFERROR(E34/E$6,0) -> 0.035714286 | F33: =IFERROR(F34/F$6,0) -> 0.033333333 | G33: =IFERROR(G34/G$6,0) -> 0.015873016 | H33: =IFERROR(H34/H$6,0) -> 0 | I33: =IFERROR(I34/I$6,0) -> 0 | J33: =IFERROR(J34/J$6,0) -> 0 | ... O33: =IFERROR(O34/O$6,0) -> 0.022496571
B34: EDUCAÇÃO | C34: =SUM(C35:C40) -> 12 | D34: =SUM(D35:D40) -> 10 | E34: =SUM(E35:E40) -> 25 | F34: =SUM(F35:F40) -> 25 | G34: =SUM(G35:G40) -> 10 | H34: =SUM(H35:H40) -> 0 | I34: =SUM(I35:I40) -> 0 | J34: =SUM(J35:J40) -> 0 | ... O34: =SUM(O35:O40) -> 82
B35: Faculdade | O35: =SUM(C35:N35) -> 0 | P35: =IFERROR(O35/$O$34,0) -> 0
B36: Curso de Idiomas | C36: 12 | E36: 15 | F36: 15 | O36: =SUM(C36:N36) -> 42 | P36: =IFERROR(O36/$O$34,0) -> 0.51219512
B37: Material Escolar | D37: 10 | O37: =SUM(C37:N37) -> 10 | P37: =IFERROR(O37/$O$34,0) -> 0.12195122
B38: Cursos profissionalizantes | E38: 10 | F38: 10 | G38: 10 | O38: =SUM(C38:N38) -> 30 | P38: =IFERROR(O38/$O$34,0) -> 0.36585366
B39: Escola filho | O39: =SUM(C39:N39) -> 0 | P39: =IFERROR(O39/$O$34,0) -> 0
B40: Outros | O40: =SUM(C40:N40) -> 0 | P40: =IFERROR(O40/$O$34,0) -> 0
B42: % EM RELAÇÃO À RECEITA | C42: =IFERROR(C43/C$6,0) -> 0.020408163 | D42: =IFERROR(D43/D$6,0) -> 0.024096386 | E42: =IFERROR(E43/E$6,0) -> 0.028571429 | F42: =IFERROR(F43/F$6,0) -> 0.026666667 | G42: =IFERROR(G43/G$6,0) -> 0.015873016 | H42: =IFERROR(H43/H$6,0) -> 0 | I42: =IFERROR(I43/I$6,0) -> 0 | J42: =IFERROR(J43/J$6,0) -> 0 | ... O42: =IFERROR(O43/O$6,0) -> 0.023319616
B43: SAÚDE | C43: =SUM(C44:C47) -> 15 | D43: =SUM(D44:D47) -> 20 | E43: =SUM(E44:E47) -> 20 | F43: =SUM(F44:F47) -> 20 | G43: =SUM(G44:G47) -> 10 | H43: =SUM(H44:H47) -> 0 | I43: =SUM(I44:I47) -> 0 | J43: =SUM(J44:J47) -> 0 | ... O43: =SUM(O44:O47) -> 85
B44: Plano de Saúde | O44: =SUM(C44:N44) -> 0 | P44: =IFERROR(O44/$O$43,0) -> 0
B45: Dentista | C45: 15 | E45: 20 | F45: 20 | O45: =SUM(C45:N45) -> 55 | P45: =IFERROR(O45/$O$43,0) -> 0.64705882
B46: Medicamentos | D46: 20 | G46: 10 | O46: =SUM(C46:N46) -> 30 | P46: =IFERROR(O46/$O$43,0) -> 0.35294118
B47: Outros | O47: =SUM(C47:N47) -> 0 | P47: =IFERROR(O47/$O$43,0) -> 0
B49: % EM RELAÇÃO À RECEITA | C49: =IFERROR(C50/C$6,0) -> 0.11564626 | D49: =IFERROR(D50/D$6,0) -> 0.06626506 | E49: =IFERROR(E50/E$6,0) -> 0.021428571 | F49: =IFERROR(F50/F$6,0) -> 0.02 | G49: =IFERROR(G50/G$6,0) -> 0 | H49: =IFERROR(H50/H$6,0) -> 0 | I49: =IFERROR(I50/I$6,0) -> 0 | J49: =IFERROR(J50/J$6,0) -> 0 | ... O49: =IFERROR(O50/O$6,0) -> 0.046639232
B50: TRANSPORTE | C50: =SUM(C51:C57) -> 85 | D50: =SUM(D51:D57) -> 55 | E50: =SUM(E51:E57) -> 15 | F50: =SUM(F51:F57) -> 15 | G50: =SUM(G51:G57) -> 0 | H50: =SUM(H51:H57) -> 0 | I50: =SUM(I51:I57) -> 0 | J50: =SUM(J51:J57) -> 0 | ... O50: =SUM(O51:O57) -> 170
B51: Ônibus / Metrô | C51: 35 | E51: 15 | F51: 15 | O51: =SUM(C51:N51) -> 65 | P51: =IFERROR(O51/$O$50,0) -> 0.38235294
B52: Carros de Aplicativos | C52: 50 | D52: 55 | O52: =SUM(C52:N52) -> 105 | P52: =IFERROR(O52/$O$50,0) -> 0.61764706
B53: Táxi | O53: =SUM(C53:N53) -> 0 | P53: =IFERROR(O53/$O$50,0) -> 0
B54: Prestação carro | O54: =SUM(C54:N54) -> 0 | P54: =IFERROR(O54/$O$50,0) -> 0
B55: Seguro | O55: =SUM(C55:N55) -> 0 | P55: =IFERROR(O55/$O$50,0) -> 0
B56: Combustível | O56: =SUM(C56:N56) -> 0 | P56: =IFERROR(O56/$O$50,0) -> 0
B57: Outros | O57: =SUM(C57:N57) -> 0 | P57: =IFERROR(O57/$O$50,0) -> 0
B59: % EM RELAÇÃO À RECEITA | C59: =IFERROR(C60/C$6,0) -> 0.040816327 | D59: =IFERROR(D60/D$6,0) -> 0.026506024 | E59: =IFERROR(E60/E$6,0) -> 0.021428571 | F59: =IFERROR(F60/F$6,0) -> 0.013333333 | G59: =IFERROR(G60/G$6,0) -> 0.015873016 | H59: =IFERROR(H60/H$6,0) -> 0 | I59: =IFERROR(I60/I$6,0) -> 0 | J59: =IFERROR(J60/J$6,0) -> 0 | ... O59: =IFERROR(O60/O$6,0) -> 0.023868313
B60: DESPESAS PESSOAIS | C60: =SUM(C61:C69) -> 30 | D60: =SUM(D61:D69) -> 22 | E60: =SUM(E61:E69) -> 15 | F60: =SUM(F61:F69) -> 10 | G60: =SUM(G61:G69) -> 10 | H60: =SUM(H61:H69) -> 0 | I60: =SUM(I61:I69) -> 0 | J60: =SUM(J61:J69) -> 0 | ... O60: =SUM(O61:O69) -> 87
B61: Alimentação | F61: 10 | G61: 10 | O61: =SUM(C61:N61) -> 20 | P61: =IFERROR(O61/$O$60,0) -> 0.22988506
B62: Higiene Pessoal | E62: 15 | O62: =SUM(C62:N62) -> 15 | P62: =IFERROR(O62/$O$60,0) -> 0.17241379
B63: Cosméticos | C63: 25 | D63: 20 | O63: =SUM(C63:N63) -> 45 | P63: =IFERROR(O63/$O$60,0) -> 0.51724138
B64: Cabeleireiro | O64: =SUM(C64:N64) -> 0 | P64: =IFERROR(O64/$O$60,0) -> 0
B65: Vestuário | C65: 5 | D65: 2 | O65: =SUM(C65:N65) -> 7 | P65: =IFERROR(O65/$O$60,0) -> 0.08045977
B66: Lavanderia | O66: =SUM(C66:N66) -> 0 | P66: =IFERROR(O66/$O$60,0) -> 0
B67: Academia | O67: =SUM(C67:N67) -> 0 | P67: =IFERROR(O67/$O$60,0) -> 0
B68: Telefone Celular | O68: =SUM(C68:N68) -> 0 | P68: =IFERROR(O68/$O$60,0) -> 0
B69: Outros | O69: =SUM(C69:N69) -> 0 | P69: =IFERROR(O69/$O$60,0) -> 0
B71: % EM RELAÇÃO À RECEITA | C71: =IFERROR(C72/C$6,0) -> 0.013605442 | D71: =IFERROR(D72/D$6,0) -> 0.024096386 | E71: =IFERROR(E72/E$6,0) -> 0.014285714 | F71: =IFERROR(F72/F$6,0) -> 0.02 | G71: =IFERROR(G72/G$6,0) -> 0.015873016 | H71: =IFERROR(H72/H$6,0) -> 0 | I71: =IFERROR(I72/I$6,0) -> 0 | J71: =IFERROR(J72/J$6,0) -> 0 | ... O71: =IFERROR(O72/O$6,0) -> 0.017832647
B72: LAZER | C72: =SUM(C73:C79) -> 10 | D72: =SUM(D73:D79) -> 20 | E72: =SUM(E73:E79) -> 10 | F72: =SUM(F73:F79) -> 15 | G72: =SUM(G73:G79) -> 10 | H72: =SUM(H73:H79) -> 0 | I72: =SUM(I73:I79) -> 0 | J72: =SUM(J73:J79) -> 0 | ... O72: =SUM(O73:O79) -> 65
B73: Restaurantes | E73: 10 | O73: =SUM(C73:N73) -> 10 | P73: =IFERROR(O73/$O$72,0) -> 0.15384615
B74: Cafés/Bares | C74: 10 | O74: =SUM(C74:N74) -> 10 | P74: =IFERROR(O74/$O$72,0) -> 0.15384615
B75: Cinema | D75: 20 | O75: =SUM(C75:N75) -> 20 | P75: =IFERROR(O75/$O$72,0) -> 0.30769231
B76: Passagens | O76: =SUM(C76:N76) -> 0 | P76: =IFERROR(O76/$O$72,0) -> 0
B77: Hotéis | F77: 15 | G77: 10 | O77: =SUM(C77:N77) -> 25 | P77: =IFERROR(O77/$O$72,0) -> 0.38461538
B78: Passeios | O78: =SUM(C78:N78) -> 0 | P78: =IFERROR(O78/$O$72,0) -> 0
B79: Outros | O79: =SUM(C79:N79) -> 0 | P79: =IFERROR(O79/$O$72,0) -> 0
B81: % EM RELAÇÃO À RECEITA | C81: =IFERROR(C82/C$6,0) -> 0.054421769 | D81: =IFERROR(D82/D$6,0) -> 0.018072289 | E81: =IFERROR(E82/E$6,0) -> 0.014285714 | F81: =IFERROR(F82/F$6,0) -> 0.013333333 | G81: =IFERROR(G82/G$6,0) -> 0.023809524 | H81: =IFERROR(H82/H$6,0) -> 0 | I81: =IFERROR(I82/I$6,0) -> 0 | J81: =IFERROR(J82/J$6,0) -> 0 | ... O81: =IFERROR(O82/O$6,0) -> 0.024691358
B82: FINANCEIRO | C82: =SUM(C83:C85) -> 40 | D82: =SUM(D83:D85) -> 15 | E82: =SUM(E83:E85) -> 10 | F82: =SUM(F83:F85) -> 10 | G82: =SUM(G83:G85) -> 15 | H82: =SUM(H83:H85) -> 0 | I82: =SUM(I83:I85) -> 0 | J82: =SUM(J83:J85) -> 0 | ... O82: =SUM(O83:O85) -> 90
B83: Cartões de Crédito | E83: 10 | F83: 10 | G83: 15 | O83: =SUM(C83:N83) -> 35 | P83: =IFERROR(O83/$O$82,0) -> 0.38888889
B84: Empréstimos | C84: 40 | D84: 15 | O84: =SUM(C84:N84) -> 55 | P84: =IFERROR(O84/$O$82,0) -> 0.61111111
B85: Outros | O85: =SUM(C85:N85) -> 0 | P85: =IFERROR(O85/$O$82,0) -> 0
B87: % EM RELAÇÃO À RECEITA | C87: =IFERROR(C88/C$6,0) -> 0.081632653 | D87: =IFERROR(D88/D$6,0) -> 0.012048193 | E87: =IFERROR(E88/E$6,0) -> 0.014285714 | F87: =IFERROR(F88/F$6,0) -> 0.026666667 | G87: =IFERROR(G88/G$6,0) -> 0.023809524 | H87: =IFERROR(H88/H$6,0) -> 0 | I87: =IFERROR(I88/I$6,0) -> 0 | J87: =IFERROR(J88/J$6,0) -> 0 | ... O87: =IFERROR(O88/O$6,0) -> 0.031550069
B88: OUTROS | C88: =SUM(C89:C93) -> 60 | D88: =SUM(D89:D93) -> 10 | E88: =SUM(E89:E93) -> 10 | F88: =SUM(F89:F93) -> 20 | G88: =SUM(G89:G93) -> 15 | H88: =SUM(H89:H93) -> 0 | I88: =SUM(I89:I93) -> 0 | J88: =SUM(J89:J93) -> 0 | ... O88: =SUM(O89:O93) -> 115
B89: Poupança | E89: 10 | F89: 20 | G89: 15 | O89: =SUM(C89:N89) -> 45 | P89: =IFERROR(O89/$O$88,0) -> 0.39130435
B90: Outros Investimentos | C90: 60 | D90: 10 | O90: =SUM(C90:N90) -> 70 | P90: =IFERROR(O90/$O$88,0) -> 0.60869565
B91: Presentes | O91: =SUM(C91:N91) -> 0 | P91: =IFERROR(O91/$O$88,0) -> 0
B92: Doações | O92: =SUM(C92:N92) -> 0 | P92: =IFERROR(O92/$O$88,0) -> 0
B93: Outros | O93: =SUM(C93:N93) -> 0 | P93: =IFERROR(O93/$O$88,0) -> 0

Sheet Gráficos
B3: [ PLANILHA ORÇAMENTO FAMILIAR ] - ANÁLISE GRÁFICA DE VALORES E GASTOS
V8: ='Orçamento'!B12 -> COMPOSIÇÃO RECEITA | W8: ='Orçamento'!O12 -> 3645
V9: ='Orçamento'!B22 -> HABITAÇÃO | W9: ='Orçamento'!O22 -> 1425 | X9: =W9/$W$17 -> 0.67248702
V10: ='Orçamento'!B34 -> EDUCAÇÃO | W10: ='Orçamento'!O34 -> 82 | X10: =W10/$W$17 -> 0.038697499
V11: ='Orçamento'!B43 -> SAÚDE | W11: ='Orçamento'!O43 -> 85 | X11: =W11/$W$17 -> 0.040113261
V12: ='Orçamento'!B50 -> TRANSPORTE | W12: ='Orçamento'!O50 -> 170 | X12: =W12/$W$17 -> 0.080226522
V13: ='Orçamento'!B60 -> DESPESAS PESSOAIS | W13: ='Orçamento'!O60 -> 87 | X13: =W13/$W$17 -> 0.041057102
V14: ='Orçamento'!B72 -> LAZER | W14: ='Orçamento'!O72 -> 65 | X14: =W14/$W$17 -> 0.030674847
V15: ='Orçamento'!B82 -> FINANCEIRO | W15: ='Orçamento'!O82 -> 90 | X15: =W15/$W$17 -> 0.042472865
V16: ='Orçamento'!B88 -> OUTROS | W16: ='Orçamento'!O88 -> 115 | X16: =W16/$W$17 -> 0.054270882
W17: =SUM(W9:W16) -> 2119
